squander/__init__.py
squander/libqgd.so
squander/utils.py
squander/IO_interfaces/Qiskit_IO.py
squander/IO_interfaces/__init__.py
squander/VQA/CMakeLists.txt
squander/VQA/__init__.py
squander/VQA/qgd_GQML_Base_Wrapper.cpp
squander/VQA/qgd_Generative_Quantum_Machine_Learning_Base.py
squander/VQA/qgd_Generative_Quantum_Machine_Learning_Base_Wrapper.cpython-312-x86_64-linux-gnu.so
squander/VQA/qgd_VQE_Base_Wrapper.cpp
squander/VQA/qgd_Variational_Quantum_Eigensolver_Base.py
squander/VQA/qgd_Variational_Quantum_Eigensolver_Base_Wrapper.cpython-312-x86_64-linux-gnu.so
squander/decomposition/CMakeLists.txt
squander/decomposition/__init__.py
squander/decomposition/qgd_N_Qubit_Decompositions_Wrapper.cpp
squander/decomposition/qgd_N_Qubit_Decompositions_Wrapper.cpython-312-x86_64-linux-gnu.so
squander/decomposition/qgd_N_Qubit_State_Preparation_adaptive.py
squander/decomposition/qgd_Wide_Circuit_Optimization.py
squander/gates/CMakeLists.txt
squander/gates/__init__.py
squander/gates/gates_Wrapper.cpp
squander/gates/gates_Wrapper.cpython-312-x86_64-linux-gnu.so
squander/gates/qgd_Circuit.py
squander/gates/qgd_Circuit_Wrapper.cpp
squander/gates/qgd_Circuit_Wrapper.cpython-312-x86_64-linux-gnu.so
squander/nn/CMakeLists.txt
squander/nn/__init__.py
squander/nn/qgd_nn.py
squander/nn/qgd_nn_Wrapper.cpp
squander/nn/qgd_nn_Wrapper.cpython-312-x86_64-linux-gnu.so
squander/partitioning/ilp.py
squander/partitioning/kahn.py
squander/partitioning/partition.py
squander/partitioning/tdag.py
squander/partitioning/tools.py
squander/src-cpp/common/Adam.cpp
squander/src-cpp/common/BFGS_Powell.cpp
squander/src-cpp/common/Bayes_Opt.cpp
squander/src-cpp/common/GrayCode.cpp
squander/src-cpp/common/Powells_method.cpp
squander/src-cpp/common/common.cpp
squander/src-cpp/common/common_DFE.cpp
squander/src-cpp/common/common_GROQ.cpp
squander/src-cpp/common/config_element.cpp
squander/src-cpp/common/dot.cpp
squander/src-cpp/common/grad_descend.cpp
squander/src-cpp/gates/squander.egg-info/PKG-INFO
squander/src-cpp/gates/squander.egg-info/SOURCES.txt
squander/src-cpp/gates/squander.egg-info/dependency_links.txt
squander/src-cpp/gates/squander.egg-info/top_level.txt
squander-1.9.6.dist-info/METADATA
squander-1.9.6.dist-info/WHEEL
squander-1.9.6.dist-info/top_level.txt
squander-1.9.6.dist-info/RECORD
squander-1.9.6.dist-info/licenses/LICENSE
squander-1.9.6.dist-info/sboms/auditwheel.cdx.json
