Metadata-Version: 2.4
Name: squander
Version: 1.9.6
Summary: C++ library with Python interface to train quantum circuits, quantum gate synthesis and state preparation.
Author-email: Peter Rakyta <peter.rakyta@ttk.elte.hu>
License: Apache-2.0
Keywords: quantum,circuits,gate,synthesis
Classifier: Intended Audience :: Developers
Classifier: Natural Language :: English
Classifier: Programming Language :: C
Classifier: Programming Language :: C++
Classifier: License :: OSI Approved :: Apache Software License
Requires-Python: >=3.8
License-File: LICENSE
Requires-Dist: numpy
Requires-Dist: scipy
Requires-Dist: networkx
Provides-Extra: dev
Requires-Dist: pytest; extra == "dev"
Dynamic: license-file
